VolFe/__init__.py
VolFe/batch_calculations.py
VolFe/calculations.py
VolFe/differential_equations.py
VolFe/equilibrium_equations.py
VolFe/isotopes.py
VolFe/melt_gas.py
VolFe/model_dependent_variables.py
volfe-1.0.dist-info/METADATA
volfe-1.0.dist-info/WHEEL
volfe-1.0.dist-info/top_level.txt
volfe-1.0.dist-info/RECORD
