Metadata-Version: 2.4
Name: VolFe
Version: 1.0
Summary: VolFe
Author: Pip Liggins, Penny Wieser
Author-email: Ery Hughes <ery.c.hughes@gmail.com>
Project-URL: Homepage, https://github.com/eryhughes/VolFe
Classifier: Operating System :: OS Independent
Classifier: Programming Language :: Python :: 3
Requires-Python: >=3.9
Requires-Dist: datetime==5.5
Requires-Dist: densityx==1.2.0
Requires-Dist: gmpy2==2.2.1
Requires-Dist: numpy<2
Requires-Dist: pandas==2.2.3
Requires-Dist: PySulfSat==1.0.6
Requires-Dist: scipy>=1.13.1
Requires-Dist: tqdm==4.67.1
Provides-Extra: dev
Requires-Dist: pytest; extra == "dev"
Requires-Dist: pytest-cov; extra == "dev"
Requires-Dist: sympy; extra == "dev"
Provides-Extra: docs
Requires-Dist: sphinx; extra == "docs"
Requires-Dist: sphinx_rtd_theme; extra == "docs"
Requires-Dist: sphinxcontrib-bibtex; extra == "docs"
Requires-Dist: nbsphinx; extra == "docs"
Requires-Dist: ipykernel; extra == "docs"
